<?xml version='1.0' encoding='utf-8'?>
<container xmlns="https://open.law/schemas/library" xmlns:cache="https://open.law/schemas/cache" xmlns:citations="https://open.law/schemas/citations" xmlns:macro="https://open.law/schemas/macro" xmlns:xs="http://www.w3.org/2001/XMLSchema" xmlns:xsl="http://www.w3.org/1999/XSL/Transform" xmlns:codified="https://open.law/schemas/codified" xmlns:codify="https://open.law/schemas/codify" xmlns:xi="http://www.w3.org/2001/XInclude">
  <prefix>Chapter</prefix>
  <num>12</num>
  <heading>Temporary Census Employment Income</heading>
  <annotations>
    <annotation type="Authority" dest="container">Article 88A, §§1A, 3, 5, 44A—53, 63—87, 124—129, and 131—137; Article 41, §§6-202 and 6-406—6-407; Family Law Article, §§<cite doc="Md. Code" path="gfl|4-501">4-501</cite>, <br/>4-513—4-516, 4-601—4-613, and 5-524; Annotated Code of Maryland</annotation>
    <annotation type="History" dest="container">Effective date:</annotation>
    <annotation type="History" dest="container" effective="2000-05-01">Regulations <cite path="|07|01|12|.01">.01</cite>—<cite path="|07|01|12|.03">.03</cite> adopted as an emergency provision effective January 1, 2000 (27:2 Md. R. 139); emergency action superseded and new Regulations <cite path="|07|01|12|.01">.01</cite>—<cite path="|07|01|12|.03">.03</cite> adopted as an emergency provision effective May 1, 2000 (27:10 Md. R. 961); emergency status expired December 31, 2000</annotation>
  </annotations>
</container>
